{"N19100312": {"username": "刘情缘", "adviewnum": 1}, "17210403": {"username": "陈思思", "adviewnum": 2}, "18270110": {"username": "郭永芬", "adviewnum": 1}, "游客": {"username": "游客", "adviewnum": 4}, "19250619": {"username": "张妹", "adviewnum": 1}, "19210203": {"username": "蔡烨慧", "adviewnum": 1}, "19650130": {"username": "赵宁文", "adviewnum": 2}, "19650102": {"username": "曾春粤", "adviewnum": 4}, "19370210": {"username": "田梓新", "adviewnum": 1}, "18050103": {"username": "戴玺颖", "adviewnum": 1}, "19460133": {"username": "谭雅茹", "adviewnum": 2}, "N19100614": {"username": "刘丽娜", "adviewnum": 1}, "N19100628": {"username": "姚玉林", "adviewnum": 1}, "19050525": {"username": "罗佳思", "adviewnum": 6}, "19120206": {"username": "公冠蓉", "adviewnum": 1}, "19120227": {"username": "王子凡", "adviewnum": 1}}