{"游客": {"username": "游客", "adviewnum": 13}, "18400210": {"username": "刘洋", "adviewnum": 1}, "18010216": {"username": "刘美佑", "adviewnum": 4}, "19250109": {"username": "龙朔军", "adviewnum": 1}, "18590223": {"username": "朱子薇", "adviewnum": 2}, "19090604": {"username": "龚晓怡", "adviewnum": 1}, "18160241": {"username": "肖雄", "adviewnum": 1}, "19160226": {"username": "莫丽琪", "adviewnum": 1}, "N18100721": {"username": "谢雄", "adviewnum": 1}, "18150127": {"username": "尧坤琳", "adviewnum": 2}, "19660136": {"username": "杨焕强", "adviewnum": 2}, "19170103": {"username": "段滢", "adviewnum": 1}, "17010142": {"username": "于雨", "adviewnum": 1}, "19040214": {"username": "金好", "adviewnum": 1}, "19040217": {"username": "梁米琪", "adviewnum": 1}, "N18100626": {"username": "谢丰年", "adviewnum": 2}, "19040223": {"username": "游客", "adviewnum": 1}, "N18100706": {"username": "黄梓晴", "adviewnum": 1}, "N19160109": {"username": "蒋素亮", "adviewnum": 1}, "19130238": {"username": "吴珺", "adviewnum": 1}, "19360231": {"username": "余鸿祥", "adviewnum": 1}, "18020122": {"username": "刘红阳", "adviewnum": 1}, "18130108": {"username": "胡梦佳", "adviewnum": 1}, "17290212": {"username": "郭钰芳", "adviewnum": 10}, "19460117": {"username": "旷彩丽", "adviewnum": 1}, "17140109": {"username": "游客", "adviewnum": 4}, "18500231": {"username": "许佳宁", "adviewnum": 1}, "17400134": {"username": "杨思秦", "adviewnum": 2}, "19090406": {"username": "奉春燕", "adviewnum": 1}, "18260115": {"username": "林瑶", "adviewnum": 1}, "19050544": {"username": "庾丹", "adviewnum": 2}, "17130105": {"username": "邓梦琪", "adviewnum": 1}}